setup.py
DSAE_Impute/__init__.py
DSAE_Impute/__main__.py
DSAE_Impute/main.py
DSAE_Impute.egg-info/PKG-INFO
DSAE_Impute.egg-info/SOURCES.txt
DSAE_Impute.egg-info/dependency_links.txt
DSAE_Impute.egg-info/entry_points.txt
DSAE_Impute.egg-info/top_level.txt
DSAE_Impute/DSAE/Discriminative_SAE.py
DSAE_Impute/DSAE/Dropout.py
DSAE_Impute/DSAE/Pre_process.py
DSAE_Impute/DSAE/To_full.py
DSAE_Impute/DSAE/__init__.py
DSAE_Impute/DSAE/noise.py
DSAE_Impute/DSAE/utils.py
DSAE_Impute/data/test.csv